politylink/__init__.py
politylink/elasticsearch/__init__.py
politylink/elasticsearch/client.py
politylink/elasticsearch/schema.py
politylink/graphql/__init__.py
politylink/graphql/client.py
politylink/graphql/schema.py
politylink/graphql/schema.sh
politylink/helpers/__init__.py
politylink/helpers/abstract_finder.py
politylink/helpers/bill_finder.py
politylink/helpers/committee_finder.py
politylink/helpers/diet_finder.py
politylink/helpers/member_finder.py
politylink/helpers/minutes_finder.py
politylink/idgen.py
politylink/nlp/__init__.py
politylink/nlp/keyphrase.py
politylink/nlp/stopwords_minutes.txt
politylink/nlp/stopwords_slothlib.txt
politylink/nlp/utils.py
politylink/utils/__init__.py
politylink/utils/bill.py
politylink/utils/common.py
politylink-0.1.90.dist-info/WHEEL
politylink-0.1.90.dist-info/METADATA
politylink-0.1.90.dist-info/RECORD
