Metadata-Version: 2.1
Name: politylink
Version: 0.1.90
Summary: 
Home-page: https://politylink.jp
Author: Mitsuki Usui
Requires-Python: >=3.8,<4.0
Classifier: Programming Language :: Python :: 3
Classifier: Programming Language :: Python :: 3.10
Classifier: Programming Language :: Python :: 3.8
Classifier: Programming Language :: Python :: 3.9
Requires-Dist: elasticsearch (>=7.9.1,<8.0.0)
Requires-Dist: elasticsearch-dsl (>=7.3.0,<8.0.0)
Requires-Dist: ginza (>=5.1,<6.0)
Requires-Dist: ja-ginza (>=5.1,<6.0)
Requires-Dist: kanjize (>=0.1.0,<0.2.0)
Requires-Dist: nltk (>=3.5,<4.0)
Requires-Dist: pandas (>=1.0.5,<2.0.0)
Requires-Dist: sgqlc (>=11.0,<12.0)
Requires-Dist: spacy (>=3.2.3,<4.0.0)
Requires-Dist: stringcase (>=1.2.0,<2.0.0)
